finntk/__init__.py
finntk/conceptnet5.py
finntk/lemmatize_en.py
finntk/utils.py
finntk/data/__init__.py
finntk/data/omorfi_normseg.py
finntk/data/omorfi_ud.py
finntk/data/wiktionary_normseg.py
finntk/data/wordnet.py
finntk/data/wordnet_pos.py
finntk/emb/__init__.py
finntk/emb/autoextend.py
finntk/emb/base.py
finntk/emb/bert.py
finntk/emb/concat.py
finntk/emb/elmo.py
finntk/emb/fasttext.py
finntk/emb/numberbatch.py
finntk/emb/utils.py
finntk/emb/word2vec.py
finntk/extr/__init__.py
finntk/extr/base.py
finntk/finnpos/__init__.py
finntk/omor/__init__.py
finntk/omor/anlys.py
finntk/omor/extract.py
finntk/omor/inst.py
finntk/omor/seg.py
finntk/omor/tok.py
finntk/scripts/__init__.py
finntk/scripts/bootstrap_all.py
finntk/scripts/prepare_enwikitionary.py
finntk/vendor/__init__.py
finntk/vendor/bert.py
finntk/vendor/cnn_50_100_512_4096_sample.json
finntk/vendor/elmo.py
finntk/vendor/conceptnet5/__init__.py
finntk/vendor/conceptnet5/uri.py
finntk/vendor/metanl/__init__.py
finntk/vendor/metanl/nltk_morphy.py
finntk/wordnet/__init__.py
finntk/wordnet/abbrv.py
finntk/wordnet/reader.py
finntk/wordnet/reader_extra.py
finntk/wordnet/utils.py
finntk/wsd/__init__.py
finntk/wsd/lesk_emb.py
finntk/wsd/lesk_pp.py
finntk/wsd/nn.py
finntk-0.0.73.dist-info/LICENSE.txt
finntk-0.0.73.dist-info/METADATA
finntk-0.0.73.dist-info/WHEEL
finntk-0.0.73.dist-info/top_level.txt
finntk-0.0.73.dist-info/RECORD
