Metadata-Version: 2.1
Name: finntk
Version: 0.0.73
Summary: Finnish NLP toolkit
Home-page: https://github.com/frankier/finntk
Author: Frankie Robertson
License: UNKNOWN
Platform: UNKNOWN
Classifier: Development Status :: 2 - Pre-Alpha
Classifier: Programming Language :: Python
Classifier: Programming Language :: Python :: 3.6
Classifier: Programming Language :: Python :: 3.7
Classifier: Programming Language :: Python :: 3.8
Requires-Dist: appdirs (>=1.4.3)
Requires-Dist: more-itertools (>=4.1.0)
Requires-Dist: nltk (>=3.3)
Requires-Dist: plumbum (>=1.6.6)
Requires-Dist: portalocker (>=1.2.1)
Requires-Dist: pyahocorasick
Requires-Dist: scikit-learn (>=0.22.0)
Requires-Dist: wordfreq (>=2.2.0)
Provides-Extra: conceptnet5
Requires-Dist: ConceptNet (>=5.7.0) ; extra == 'conceptnet5'
Provides-Extra: dev
Requires-Dist: flake8 (>=3.5.0) ; extra == 'dev'
Requires-Dist: hypothesis ; extra == 'dev'
Requires-Dist: pytest ; extra == 'dev'
Requires-Dist: setuptools (>=38.6.0) ; extra == 'dev'
Requires-Dist: twine (>=1.11.0) ; extra == 'dev'
Requires-Dist: wheel (>=0.31.0) ; extra == 'dev'
Provides-Extra: docs
Requires-Dist: recommonmark ; extra == 'docs'
Requires-Dist: sphinx (>=1.5) ; extra == 'docs'
Requires-Dist: sphinx-autodoc-typehints ; extra == 'docs'
Requires-Dist: sphinx-rtd-theme ; extra == 'docs'
Provides-Extra: emb
Requires-Dist: gensim (>=3.4.0) ; extra == 'emb'
Provides-Extra: gpu
Requires-Dist: pytorch-pretrained-bert ; extra == 'gpu'
Requires-Dist: torch (>=1.0.0) ; extra == 'gpu'
